{
    "products": [
      { 
          "id": "1",
          "title": "لپ تاپ 13.6 اینچ اپل مدل MacBook Air-MLY43 M2 2022 LLA", 
          "image": "https://dkstatics-public.digikala.com/digikala-products/34a1d09520fbc079f21b37dc1ef9060c0963468b_1671475078.jpg?x-oss-process=image/resize,m_lfit,h_800,w_800/quality,q_90",
          "price": 78590000,
          "discount": 15,
          "description": "چندی پیش شرکت اپل از نسل جدید لپ تاپ‌های MacBook خود رونمایی کرد. این لپ تاپ‌ها در کانفیگ‌ها و مدل‌های مختلف معرفی شدند و بالطبع هر کدام با قیمت‌های مختلف در دسترس علاقه‌مندان قرار گرفته‌اند. از جمله لپ تاپ‌های جدید شرکت اپل که از طراحی زیبا و مشخصات سخت افزاری چشمگیر بهره‌مند است، می‌توان به لپ تاپ مدل MacBook Air-MLY43 M2 2022 LLA اشاره کرد. این لپ تاپ از بدنه‌ی بسیار با کیفیت آلومینیومی و طراحی ظاهری ساده اما جذابی بهره می‌برد. همچنین، میزان 512 گیگابایت حافظه‌ی پرسرعت SSD می‌تواند سرعت بسیار بالای این لپ تاپ در انجام امور مختلف را تضمین کند. ناگفته نماند که شرکت اپل برای این لپ تاپ از 8 گیگابایت رم از نوع Unified استفاده کرده است. همچنین، پردازنده‌ی مرکزی این لپ تاپ با مدل M2 8‑core دارای هشت هسته (4 هسته‌ی Performance و 4 هسته‌ی Efficiency) است و می‌تواند عملکرد خیره کننده‌ای از خود به نمایش بگذارد.",
          "category": "لپ تاپ",
          "rating": {
              "rate": 4.3,
              "count": 9
          },
          "specifications": {
              "جنس": "سیلیکون",
              "دور موتور": 2000,
              "وزن": "1.24 کیلوگرم",
              "پردازنده": "Apple M2",
              "حافظه داخلی": "512GB SSD",
              "رم": "8GB Unified Memory"
          },
          "colors": [
            {
                "name": "نقره‌ای",
                "colorCode": "#C0C0C0"
            },
            {
                "name": "خاکستری فضایی",
                "colorCode": "#3D3C3A"
            },
            {
                "name": "طلایی",
                "colorCode": "#FFD700"
            }
        ]
      },

      { 
        "id": "2",
        "title": "لپ تاپ 13 اینچی اپل مدل MacBook Air MGN93 2020", 
        "image":"https://dkstatics-public.digikala.com/digikala-products/e860fbe53fa70894ed9d8ab11d73f68b6cc0b7e1_1672051160.jpg?x-oss-process=image/resize,m_lfit,h_800,w_800/quality,q_90",
        "price": 55360000 ,
        "discount":20,
        "description":"موردانتظارترین و تأثیرگذارترین رویداد اپل در سال 2020، نخستین کامپیوتر‌های مک با پردازنده‌ی اختصاصی این شرکت را به‌ارمغان آورد. مک‌بوک ایر نخستین لپ‌تاپ اپل با پردازنده‌ی مبتنی‌بر ARM کوپرتینونشین‌ها موسوم به M1 خواهد بود.همان‌طور که انتظار می‌رفت مک‌بوک ایر به‌لحاظ ظاهر و طراحی هیچ تفاوتی با نسخه‌ی اینتل ندارد و همانند گذشته است. تغییرات اصلی مک‌ بوک ایر در داخل آن رخ می‌دهد؛ جایی‌که تراشه اختصاصی M1 توان پردازشی موردنیاز کاربر را با بهره‌وری بالاتر و مصرف انرژی کمتر فراهم می‌سازد. این تراشه در دو نسخه‌ با گرافیک 7 یا 8 هسته‌ای درون مک بوک ایر به‌کار می‌رود؛ اما در هر دو نسخه، پردازنده‌ی مرکزی 8 هسته‌ای و واحد پردازش عصبی 16 هسته‌ای دردسترس هستند. به‌مدد بهینگی بسیار بیشتر تراشه‌‌ی اختصاصی M1، کوپرتینونشین‌ها مک‌ بوک ایر را با سیستم خنک‌کننده‌ی پسیو (بدون فن) تولید می‌کنند.اپل می‌گوید CPU داخل تراشه‌ی M1 به‌مدد 4 هسته‌ی قدرتمند و 4 هسته‌ی کم‌مصرفش در مجموع بالغ‌بر 3٫5 برابر و GPU هشت هسته‌ای آن نیز تا 5 برابر سریع‌تر از نسل گذشته عمل می‌کنند. از سوی دیگر به‌لطف واحد پردازش عصبی 16 هسته‌ای M1 پردازش‌های مبتنی‌بر یادگیری ماشین نظیر تشخیص چهره یا شناسایی اجسام تا 9 برابر سریع‌تر صورت می‌گیرد. براساس ادعای اپل، تراشه‌ی M1 موجود در داخل مک بوک ایر از «98 درصد لپ‌تاپ‌های فروخته‌شده در سال گذشته» سریع‌تر است. اپل می‌گوید به‌لطف کنترلر حافظه‌ی موجود در M1 و حافظه‌های جدید، ماژول‌های SSD مک‌بوک ایر بالغ‌بر 2 برابر سریع‌تر از گذشته هستند.اولترابوک محبوب اپل جک 3٫5 میلی‌متری هدفون و دو پورت USB 4 با پشتیبانی از USB 3.1 Gen 2 (پهنای باند 10 گیگابیت‌برثانیه) و تاندربولت 3 (پهنای باند 40 گیگابیت‌برثانیه) را دراختیار کاربر می‌گذارد. این پورت‌‌ها هم‌اکنون از گرافیک اکسترنال پشتیبانی نمی‌کنند؛ اما به‌کمک آن‌ها می‌توان یک نمایشگر اکسترنال با وضوح 6K و نرخ نوسازی 60 هرتز را به مک‌بوک ایر متصل کرد.مک بوک ایر اسپیکرهای استریو با پشتیبانی از دالبی اتموس، ماژول Wi-Fi 6 و بلوتوث 5 را در بطن خود دارد. این لپ‌تاپ همانند گذشته از وب‌کم 720p استفاده می‌کند؛ اما اکنون به‌لطف پردازنده‌ی سیگنال تصویر داخل تراشه‌ی M1 تصاویر را با نویز کمتر و گستره‌ی دینامیکی وسیع‌تری ثبت می‌کند.",
        "category":"لپ تاپ",
        "rating":{
            "rate":5.3,
            "count":20
        },
          "specifications": {
              "جنس": "سیلیکون",
              "دور موتور": 2000,
              "وزن": "1.24 کیلوگرم",
              "پردازنده": "Apple M2",
              "حافظه داخلی": "512GB SSD",
              "رم": "8GB Unified Memory"
          },
          "colors": [
            {
                "name": "نقره‌ای",
                "colorCode": "#C0C0C0"
            },
            {
                "name": "خاکستری فضایی",
                "colorCode": "#3D3C3A"
            },
            {
                "name": "طلایی",
                "colorCode": "#FFD700"
            }
        ]
      },
      { 
        "id": "3",
        "title": "لپ تاپ 13 اینچی اپل مدل MacBook Air MGND3 2020-M1 8GB 256SSD", 
        "image":"https://dkstatics-public.digikala.com/digikala-products/837d3b93c562ae5448f3f3bcedddd3e531f0b064_1672051144.jpg?x-oss-process=image/resize,m_lfit,h_800,w_800/quality,q_90",
        "price": 78590000 ,
        "discount":15,
        "description":"لپ تاپ 13 اینچی اپل مدل MacBook Air MGND3 2020 یکی از جدیدترین محصولات شرکت اپل است که با ویژگی‌های بسیار جذاب و منحصر به فرد خود، توانسته است توجه بسیاری از کاربران را به خود جلب کند. این لپ تاپ دارای صفحه نمایش 13.3 اینچی IPS LED-backlit LCD با کیفیت بسیار بالا، پردازنده Apple M1 chip قدرتمند، حافظه داخلی 256 گیگابایت SSD و باتری با ظرفیت حداکثر تا 15 ساعت برای وب گردی است. صفحه نمایش این لپ‌تاپ از نوع IPS LED-backlit LCD با اندازه 13. 3 اینچ و دقت QHD|2560x1600 است. این صفحه نمایش دارای نسبت تصویر 16 به 10، روشنایی 400 nights و قابلیت‌های Wide Color P3 True Tone Technoloy است. همچنین دارای وبکم 720p FaceTime HD camera، بلندگوهای استریو داخلی و تاچ پد با تکنولوژی Force Touch است. از دیگر ویژگی‌های ارتباطی این دستگاه می‌توان به دارا بودن درگاه USB 4. 0 و شبکه بی‌سیم Wi-Fi 802.11ax اشاره کرد. استفاده از مواد با کیفیت برای ساخت این لپ‌تاپ و ارتقاء قابلیت‌های آن توسط شرکت گارانتی‌کننده، این محصول را به یک انتخاب مناسب برای استفاده روزمره تبدیل کرده است. طراحی داخلی این لپ‌تاپ شامل مشخصاتی مانند صفحه نمایش IPS LED-backlit LCD با دقت QHD|2560x1600 و مجهز به تکنولوژی Force Touch با پشتیبانی کامل از انواع فرمان‌های چند لمسی تا فرمان‌های سه و چهارانگشتی است. همچنین دارای دو درگاه USB-C و قابلیت خروجی Thunderbolt 3 از طریق درگاه USB-C و خروجی DisplayPort از طریق درگاه USB-C است. طراحی خارجی این لپ‌تاپ شامل وزن و ابعاد مناسب برای استفاده عمومی و باتری لیتیوم پلیمر با ظرفیت 49. 9 وات ساعت که حداکثر تا 15 ساعت باتری را برای وب گردی می‌تواند فراهم کند. لپ‌تاپ 13 اینچی اپل مک‌بوک ایر از نظر کارایی و عمل‌کرد دارای ویژگی‌های بسیار مناسبی است که به کاربران این امکان را می‌دهد تا از تجربه استفاده بسیار خوبی برخوردار شوند. این لپ‌تاپ از پردازنده Apple M1 chip با محدوده سرعت 2.8 گیگاهرتز و بیشتر و حافظه Cache 12 مگابایت استفاده می‌کند که باعث سرعت بالا و عمل‌کرد قوی دستگاه می‌شود. در مورد کارایی حافظه داخلی، این لپ‌تاپ از حافظه داخلی SSD با فناوری PCIe-based onboard استفاده می‌",
        "category":"لپ تاپ",
        "rating":{
            "rate":3.3,
            "count":9
        },
        "specifications": {
            "جنس": "سیلیکون",
            "دور موتور": 2000,
            "وزن": "1.24 کیلوگرم",
            "پردازنده": "Apple M2",
            "حافظه داخلی": "512GB SSD",
            "رم": "8GB Unified Memory"
        },
          "colors": [
            {
                "name": "نقره‌ای",
                "colorCode": "#C0C0C0"
            },
            {
                "name": "خاکستری فضایی",
                "colorCode": "#3D3C3A"
            },
            {
                "name": "طلایی",
                "colorCode": "#FFD700"
            }
        ]
      },
      { 
        "id": "4",
        "title": "لپ تاپ 13.6 اینچ اپل مدل MacBook Air-MLY13 M2 2022 LLA", 
        "image":"https://dkstatics-public.digikala.com/digikala-products/f1e16fc7ed99ecd45c63eb6cc1092ccab6f27bdf_1671475225.jpg?x-oss-process=image/resize,m_lfit,h_800,w_800/quality,q_90",
        "price": 65990000 ,
        "discount":8,
        "description":"چندی پیش شرکت اپل از نسل جدید لپ تاپ‌های MacBook خود رونمایی کرد. این لپ تاپ‌ها در کانفیگ‌ها و مدل‌های مختلف معرفی شدند و بالطبع هر کدام با قیمت‌های مختلف در دسترس علاقه‌مندان قرار گرفته‌اند. از جمله لپ تاپ‌های جدید شرکت اپل که از طراحی زیبا و مشخصات سخت افزاری چشمگیر بهره‌مند است، می‌توان به لپ تاپ مدل MacBook Air-MLY13 M2 2022 LLA اشاره کرد. این لپ تاپ از بدنه‌ی بسیار با کیفیت آلومینیومی و طراحی ظاهری ساده اما جذابی بهره می‌برد. همچنین، میزان 256 گیگابایت حافظه‌ی پرسرعت SSD می‌تواند سرعت بسیار بالای این لپ تاپ در انجام امور مختلف را تضمین کند. ناگفته نماند که شرکت اپل برای این لپ تاپ از 8 گیگابایت رم از نوع Unified استفاده کرده است. همچنین، پردازنده‌ی مرکزی این لپ تاپ با مدل M2 8‑core دارای هشت هسته (4 هسته‌ی Performance و 4 هسته‌ی Efficiency) است و می‌تواند عملکرد خیره کننده‌ای از خود به نمایش بگذارد.",
        "category":"لپ تاپ",
        "rating":{
            "rate":4.3,
            "count":9
        },
        "specifications": {
            "جنس": "سیلیکون",
            "دور موتور": 2000,
            "وزن": "1.24 کیلوگرم",
            "پردازنده": "Apple M2",
            "حافظه داخلی": "512GB SSD",
            "رم": "8GB Unified Memory"
        },
            "colors": [
            {
                "name": "نقره‌ای",
                "colorCode": "#C0C0C0"
            },
            {
                "name": "خاکستری فضایی",
                "colorCode": "#3D3C3A"
            },
            {
                "name": "طلایی",
                "colorCode": "#FFD700"
            }
        ]
      },
      { 
        "id": "5",
        "title": "لپ تاپ 15.3 اینچی اپل مدل MacBook Air MRYQ3 2024 LLA-M3-8GB RAM-512GB SSD", 
        "image":"https://dkstatics-public.digikala.com/digikala-products/5c2368648b37a98c33c513316c71f79436db6a5a_1723625352.jpg?x-oss-process=image/resize,m_lfit,h_800,w_800/quality,q_90",
        "price": 75990000 ,
        "discount":0,
        "description":"چندی پیش شرکت اپل از نسل جدید لپ تاپ‌های MacBook خود رونمایی کرد. این لپ تاپ‌ها در کانفیگ‌ها و مدل‌های مختلف معرفی شدند و بالطبع هر کدام با قیمت‌های مختلف در دسترس علاقه‌مندان قرار گرفته‌اند. از جمله لپ تاپ‌های جدید شرکت اپل که از طراحی زیبا و مشخصات سخت افزاری چشمگیر بهره‌مند است، می‌توان به لپ تاپ مدل MacBook Air-MLY13 M2 2022 LLA اشاره کرد. این لپ تاپ از بدنه‌ی بسیار با کیفیت آلومینیومی و طراحی ظاهری ساده اما جذابی بهره می‌برد. همچنین، میزان 256 گیگابایت حافظه‌ی پرسرعت SSD می‌تواند سرعت بسیار بالای این لپ تاپ در انجام امور مختلف را تضمین کند. ناگفته نماند که شرکت اپل برای این لپ تاپ از 8 گیگابایت رم از نوع Unified استفاده کرده است. همچنین، پردازنده‌ی مرکزی این لپ تاپ با مدل M2 8‑core دارای هشت هسته (4 هسته‌ی Performance و 4 هسته‌ی Efficiency) است و می‌تواند عملکرد خیره کننده‌ای از خود به نمایش بگذارد.",
        "category":"لپ تاپ",
        "rating":{
            "rate":4.3,
            "count":9
        },
        "specifications": {
            "جنس": "سیلیکون",
            "دور موتور": 2000,
            "وزن": "1.24 کیلوگرم",
            "پردازنده": "Apple M2",
            "حافظه داخلی": "512GB SSD",
            "رم": "8GB Unified Memory"
        },
          "colors": [
            {
                "name": "نقره‌ای",
                "colorCode": "#C0C0C0"
            },
            {
                "name": "خاکستری فضایی",
                "colorCode": "#3D3C3A"
            },
            {
                "name": "طلایی",
                "colorCode": "#FFD700"
            }
        ]
      },
      { 
        "id": "6",
        "title": "لپ تاپ 13.6 اینچ اپل مدل MacBook Air-MLY43 M2 2022 LLA ", 
        "image":"https://dkstatics-public.digikala.com/digikala-products/1103d366e8d73bc155a7e1be7f926f0d2bfca503_1671475208.jpg?x-oss-process=image/resize,m_lfit,h_800,w_800/quality,q_90",
        "price": 85990000 ,
        "discount":2,
        "description":"چندی پیش شرکت اپل از نسل جدید لپ تاپ‌های MacBook خود رونمایی کرد. این لپ تاپ‌ها در کانفیگ‌ها و مدل‌های مختلف معرفی شدند و بالطبع هر کدام با قیمت‌های مختلف در دسترس علاقه‌مندان قرار گرفته‌اند. از جمله لپ تاپ‌های جدید شرکت اپل که از طراحی زیبا و مشخصات سخت افزاری چشمگیر بهره‌مند است، می‌توان به لپ تاپ مدل MacBook Air-MLY13 M2 2022 LLA اشاره کرد. این لپ تاپ از بدنه‌ی بسیار با کیفیت آلومینیومی و طراحی ظاهری ساده اما جذابی بهره می‌برد. همچنین، میزان 256 گیگابایت حافظه‌ی پرسرعت SSD می‌تواند سرعت بسیار بالای این لپ تاپ در انجام امور مختلف را تضمین کند. ناگفته نماند که شرکت اپل برای این لپ تاپ از 8 گیگابایت رم از نوع Unified استفاده کرده است. همچنین، پردازنده‌ی مرکزی این لپ تاپ با مدل M2 8‑core دارای هشت هسته (4 هسته‌ی Performance و 4 هسته‌ی Efficiency) است و می‌تواند عملکرد خیره کننده‌ای از خود به نمایش بگذارد.",
        "category":"لپ تاپ",
        "rating":{
            "rate":4.3,
            "count":9
        },
        "specifications": {
            "جنس": "سیلیکون",
            "دور موتور": 2000,
            "وزن": "1.24 کیلوگرم",
            "پردازنده": "Apple M2",
            "حافظه داخلی": "512GB SSD",
            "رم": "8GB Unified Memory"
        },
          "colors": [
            {
                "name": "نقره‌ای",
                "colorCode": "#C0C0C0"
            },
            {
                "name": "خاکستری فضایی",
                "colorCode": "#3D3C3A"
            },
            {
                "name": "طلایی",
                "colorCode": "#FFD700"
            }
        ]
      }
    
    ],
    "slider":[
      {
        "id":"1",
        "image":"https://nonegar2.ir/km/slider.gif",
        "alt":"اسلایدر1",
        "link":""
      },
      {
        "id":"2",
        "image":"https://nonegar2.ir/km/slide2.webp",
        "alt":"اسلایدر2",
        "link":""
      }
      ,
      {
        "id":"3",
        "image":"https://nonegar2.ir/km/slide3.jpg",
        "alt":"اسلایدر3",
        "link":""
      }
    ]

  }